Workbook

Sheet Inputs
A1: EVA & COMPOUNDER ANALYSIS - INPUT DATA
A3: CAPM ASSUMPTIONS
A4: Risk-Free Rate | B4: 0.0425
A5: Market Risk Premium | B5: 0.055
A7: Company | B7: Period | C7: EBIT ($M) | D7: Net Income ($M) | E7: Equity ($M) | F7: Debt ($M) | G7: Total Assets ($M) | H7: Tax Rate | I7: Beta | J7: Cost of Debt | K7: Prev EBIT ($M) | L7: Prev Equity ($M) | M7: Prev Debt ($M) | N7: Prev Tax Rate
A8: Veeva (VEEV) | B8: FY2026 (Jan 2026) | C8: 1438 | D8: 1121 | E8: 6500 | F8: 0 | G8: 8500 | H8: 0.22 | I8: 1.08 | J8: 0 | K8: 691.4 | L8: 5832 | M8: 0 | N8: 0.223
A9: ServiceNow (NOW) | B9: FY2025 (Dec 2025) | C9: 1824 | D9: 1748 | E9: 12964 | F9: 1491 | G9: 26038 | H9: 0.227 | I9: 0.97 | J9: 0.0153 | K9: 1364 | L9: 9609 | M9: 2278 | N9: 0.18
A10: Intuit (INTU) | B10: FY2025 (Jul 2025) | C10: 4923 | D10: 3869 | E10: 19710 | F10: 5973 | G10: 36958 | H10: 0.2 | I10: 1.28 | J10: 0.048 | K10: 3630 | L10: 18436 | M10: 6038 | N10: 0.17
A11: Adobe (ADBE) | B11: FY2025 (Nov 2025) | C11: 8706 | D11: 7130 | E11: 11623 | F11: 6210 | G11: 29496 | H11: 0.184 | I11: 1.53 | J11: 0.0424 | K11: 6741 | L11: 14105 | M11: 5628 | N11: 0.198
A12: Shopify (SHOP) | B12: FY2025 (Dec 2025) | C12: 1468 | D12: 1231 | E12: 13473 | F12: 188 | G12: 15189 | H12: 0.184 | I12: 2.82 | J12: 0.045 | K12: 1075 | L12: 11558 | M12: 918 | N12: 0.094
A13: Axon (AXON) | B13: FY2025 (Dec 2025) | C13: -62.1 | D13: 124.7 | E13: 3243 | F13: 1811 | G13: 7000 | H13: 0.21 | I13: 1.52 | J13: 0.052 | K13: 58.5 | L13: 2328 | M13: 690 | N13: 0.012
A14: BillionToOne (BLLN) | B14: FY2025 (Dec 2025) | C14: 16 | D14: 2.9 | E14: 480.1 | F14: 52.5 | G14: 600 | H14: 0.04 | I14: 1.34 | J14: 0.08 | K14: -47.15 | L14: 168 | M14: 109 | N14: 0.04
A15: Intuitive Surgical (ISRG) | B15: FY2025 (Dec 2025) | C15: 2949 | D15: 2900 | E15: 17942 | F15: 0 | G15: 20459 | H15: 0.215 | I15: 1.69 | J15: 0 | K15: 1767 | L15: 13397 | M15: 0 | N15: 0.1258
A16: Eli Lilly (LLY) | B16: FY2025 (Dec 2025) | C16: 28300 | D16: 20600 | E16: 26535 | F16: 42510 | G16: 112476 | H16: 0.19 | I16: 0.43 | J16: 0.026 | K16: 12899 | L16: 14272 | M16: 33644 | N16: 0.165
A17: Palantir (PLTR) | B17: FY2025 (Dec 2025) | C17: 1414 | D17: 1625 | E17: 7500 | F17: 0 | G17: 8900 | H17: 0.015 | I17: 1.69 | J17: 0 | K17: 310.4 | L17: 5094 | M17: 0 | N17: 0.0435
A18: Tesla (TSLA) | B18: FY2025 (Dec 2025) | C18: 4355 | D18: 3794 | E18: 82900 | F18: 1800 | G18: 137806 | H18: 0.27 | I18: 2.07 | J18: 0.025 | K18: 8891 | L18: 72913 | M18: 7878 | N18: 0.204
A19: Constellation Software (CSU) | B19: FY2025 (Dec 2025) | C19: 1895 | D19: 512 | E19: 4267 | F19: 4554 | G19: 16171 | H19: 0.376 | I19: 0.72 | J19: 0.052 | K19: 1463 | L19: 3288 | M19: 4166 | N19: 0.241
... A21: Comfort Systems (FIX) | B21: FY2025 (Dec 2025) | C21: 1315 | D21: 1023 | E21: 2449 | F21: 145 | G21: 6441 | H21: 0.209 | I21: 1.58 | J21: 0.062 | K21: 749.4 | L21: 1705 | M21: 68.3 | N21: 0.2162

Sheet Calculations
A1: EVA & COMPOUNDER CALCULATIONS
A3: Company | B3: Cost of Equity | C3: Capital Invested ($M) | D3: Equity Weight | E3: Debt Weight | F3: WACC | G3: NOPAT ($M) | H3: ROIC | I3: ROE | J3: ROA | K3: Prev NOPAT ($M) | L3: Prev Capital ($M) | M3: Delta NOPAT ($M) | N3: Delta Capital ($M) | O3: ROIIC
A4: =Inputs!A8 -> Veeva (VEEV) | B4: =Inputs!$B$4+Inputs!I8*Inputs!$B$5 -> 0.1019 | C4: =Inputs!E8+Inputs!F8 -> 6500 | D4: =IF(C4=0,0,Inputs!E8/C4) -> 1 | E4: =IF(C4=0,0,Inputs!F8/C4) -> 0 | F4: =D4*B4+E4*Inputs!J8*(1-Inputs!H8) -> 0.1019 | G4: =Inputs!C8*(1-Inputs!H8) -> 1121.64 | H4: =IF(C4=0,0,G4/C4) -> 0.17256 | I4: =IF(Inputs!E8=0,0,Inputs!D8/Inputs!E8) -> 0.17246154 | J4: =IF(Inputs!G8=0,0,Inputs!D8/Inputs!G8) -> 0.13188235 | K4: =Inputs!K8*(1-Inputs!N8) -> 537.2178 | L4: =Inputs!L8+Inputs!M8 -> 5832 | M4: =G4-K4 -> 584.4222 | N4: =C4-L4 -> 668 | O4: =IF(ABS(N4)<10,"N/M",M4/N4) -> 0.87488353
A5: =Inputs!A9 -> ServiceNow (NOW) | B5: =Inputs!$B$4+Inputs!I9*Inputs!$B$5 -> 0.09585 | C5: =Inputs!E9+Inputs!F9 -> 14455 | D5: =IF(C5=0,0,Inputs!E9/C5) -> 0.8968523 | E5: =IF(C5=0,0,Inputs!F9/C5) -> 0.1031477 | F5: =D5*B5+E5*Inputs!J9*(1-Inputs!H9) -> 0.087183211 | G5: =Inputs!C9*(1-Inputs!H9) -> 1409.952 | H5: =IF(C5=0,0,G5/C5) -> 0.097540782 | I5: =IF(Inputs!E9=0,0,Inputs!D9/Inputs!E9) -> 0.13483493 | J5: =IF(Inputs!G9=0,0,Inputs!D9/Inputs!G9) -> 0.067132652 | K5: =Inputs!K9*(1-Inputs!N9) -> 1118.48 | L5: =Inputs!L9+Inputs!M9 -> 11887 | M5: =G5-K5 -> 291.472 | N5: =C5-L5 -> 2568 | O5: =IF(ABS(N5)<10,"N/M",M5/N5) -> 0.11350156
A6: =Inputs!A10 -> Intuit (INTU) | B6: =Inputs!$B$4+Inputs!I10*Inputs!$B$5 -> 0.1129 | C6: =Inputs!E10+Inputs!F10 -> 25683 | D6: =IF(C6=0,0,Inputs!E10/C6) -> 0.76743371 | E6: =IF(C6=0,0,Inputs!F10/C6) -> 0.23256629 | F6: =D6*B6+E6*Inputs!J10*(1-Inputs!H10) -> 0.095573811 | G6: =Inputs!C10*(1-Inputs!H10) -> 3938.4 | H6: =IF(C6=0,0,G6/C6) -> 0.15334657 | I6: =IF(Inputs!E10=0,0,Inputs!D10/Inputs!E10) -> 0.1962963 | J6: =IF(Inputs!G10=0,0,Inputs!D10/Inputs!G10) -> 0.1046864 | K6: =Inputs!K10*(1-Inputs!N10) -> 3012.9 | L6: =Inputs!L10+Inputs!M10 -> 24474 | M6: =G6-K6 -> 925.5 | N6: =C6-L6 -> 1209 | O6: =IF(ABS(N6)<10,"N/M",M6/N6) -> 0.76550868
A7: =Inputs!A11 -> Adobe (ADBE) | B7: =Inputs!$B$4+Inputs!I11*Inputs!$B$5 -> 0.12665 | C7: =Inputs!E11+Inputs!F11 -> 17833 | D7: =IF(C7=0,0,Inputs!E11/C7) -> 0.65176919 | E7: =IF(C7=0,0,Inputs!F11/C7) -> 0.34823081 | F7: =D7*B7+E7*Inputs!J11*(1-Inputs!H11) -> 0.094594797 | G7: =Inputs!C11*(1-Inputs!H11) -> 7104.096 | H7: =IF(C7=0,0,G7/C7) -> 0.39836797 | I7: =IF(Inputs!E11=0,0,Inputs!D11/Inputs!E11) -> 0.61343887 | J7: =IF(Inputs!G11=0,0,Inputs!D11/Inputs!G11) -> 0.24172769 | K7: =Inputs!K11*(1-Inputs!N11) -> 5406.282 | L7: =Inputs!L11+Inputs!M11 -> 19733 | M7: =G7-K7 -> 1697.814 | N7: =C7-L7 -> -1900 | O7: =IF(ABS(N7)<10,"N/M",M7/N7) -> -0.89358632
A8: =Inputs!A12 -> Shopify (SHOP) | B8: =Inputs!$B$4+Inputs!I12*Inputs!$B$5 -> 0.1976 | C8: =Inputs!E12+Inputs!F12 -> 13661 | D8: =IF(C8=0,0,Inputs!E12/C8) -> 0.9862382 | E8: =IF(C8=0,0,Inputs!F12/C8) -> 0.013761804 | F8: =D8*B8+E8*Inputs!J12*(1-Inputs!H12) -> 0.195386 | G8: =Inputs!C12*(1-Inputs!H12) -> 1197.888 | H8: =IF(C8=0,0,G8/C8) -> 0.087686699 | I8: =IF(Inputs!E12=0,0,Inputs!D12/Inputs!E12) -> 0.091367921 | J8: =IF(Inputs!G12=0,0,Inputs!D12/Inputs!G12) -> 0.081045493 | K8: =Inputs!K12*(1-Inputs!N12) -> 973.95 | L8: =Inputs!L12+Inputs!M12 -> 12476 | M8: =G8-K8 -> 223.938 | N8: =C8-L8 -> 1185 | O8: =IF(ABS(N8)<10,"N/M",M8/N8) -> 0.18897722
A9: =Inputs!A13 -> Axon (AXON) | B9: =Inputs!$B$4+Inputs!I13*Inputs!$B$5 -> 0.1261 | C9: =Inputs!E13+Inputs!F13 -> 5054 | D9: =IF(C9=0,0,Inputs!E13/C9) -> 0.64166996 | E9: =IF(C9=0,0,Inputs!F13/C9) -> 0.35833004 | F9: =D9*B9+E9*Inputs!J13*(1-Inputs!H13) -> 0.09563478 | G9: =Inputs!C13*(1-Inputs!H13) -> -49.059 | H9: =IF(C9=0,0,G9/C9) -> -0.0097069648 | I9: =IF(Inputs!E13=0,0,Inputs!D13/Inputs!E13) -> 0.038452051 | J9: =IF(Inputs!G13=0,0,Inputs!D13/Inputs!G13) -> 0.017814286 | K9: =Inputs!K13*(1-Inputs!N13) -> 57.798 | L9: =Inputs!L13+Inputs!M13 -> 3018 | M9: =G9-K9 -> -106.857 | N9: =C9-L9 -> 2036 | O9: =IF(ABS(N9)<10,"N/M",M9/N9) -> -0.052483792
A10: =Inputs!A14 -> BillionToOne (BLLN) | B10: =Inputs!$B$4+Inputs!I14*Inputs!$B$5 -> 0.1162 | C10: =Inputs!E14+Inputs!F14 -> 532.6 | D10: =IF(C10=0,0,Inputs!E14/C10) -> 0.90142696 | E10: =IF(C10=0,0,Inputs!F14/C10) -> 0.098573038 | F10: =D10*B10+E10*Inputs!J14*(1-Inputs!H14) -> 0.11231622 | G10: =Inputs!C14*(1-Inputs!H14) -> 15.36 | H10: =IF(C10=0,0,G10/C10) -> 0.028839655 | I10: =IF(Inputs!E14=0,0,Inputs!D14/Inputs!E14) -> 0.0060404082 | J10: =IF(Inputs!G14=0,0,Inputs!D14/Inputs!G14) -> 0.0048333333 | K10: =Inputs!K14*(1-Inputs!N14) -> -45.264 | L10: =Inputs!L14+Inputs!M14 -> 277 | M10: =G10-K10 -> 60.624 | N10: =C10-L10 -> 255.6 | O10: =IF(ABS(N10)<10,"N/M",M10/N10) -> 0.2371831
A11: =Inputs!A15 -> Intuitive Surgical (ISRG) | B11: =Inputs!$B$4+Inputs!I15*Inputs!$B$5 -> 0.13545 | C11: =Inputs!E15+Inputs!F15 -> 17942 | D11: =IF(C11=0,0,Inputs!E15/C11) -> 1 | E11: =IF(C11=0,0,Inputs!F15/C11) -> 0 | F11: =D11*B11+E11*Inputs!J15*(1-Inputs!H15) -> 0.13545 | G11: =Inputs!C15*(1-Inputs!H15) -> 2314.965 | H11: =IF(C11=0,0,G11/C11) -> 0.12902491 | I11: =IF(Inputs!E15=0,0,Inputs!D15/Inputs!E15) -> 0.16163193 | J11: =IF(Inputs!G15=0,0,Inputs!D15/Inputs!G15) -> 0.14174691 | K11: =Inputs!K15*(1-Inputs!N15) -> 1544.7114 | L11: =Inputs!L15+Inputs!M15 -> 13397 | M11: =G11-K11 -> 770.2536 | N11: =C11-L11 -> 4545 | O11: =IF(ABS(N11)<10,"N/M",M11/N11) -> 0.16947274
A12: =Inputs!A16 -> Eli Lilly (LLY) | B12: =Inputs!$B$4+Inputs!I16*Inputs!$B$5 -> 0.06615 | C12: =Inputs!E16+Inputs!F16 -> 69045 | D12: =IF(C12=0,0,Inputs!E16/C12) -> 0.38431458 | E12: =IF(C12=0,0,Inputs!F16/C12) -> 0.61568542 | F12: =D12*B12+E12*Inputs!J16*(1-Inputs!H16) -> 0.038388744 | G12: =Inputs!C16*(1-Inputs!H16) -> 22923 | H12: =IF(C12=0,0,G12/C12) -> 0.33200087 | I12: =IF(Inputs!E16=0,0,Inputs!D16/Inputs!E16) -> 0.77633314 | J12: =IF(Inputs!G16=0,0,Inputs!D16/Inputs!G16) -> 0.18315018 | K12: =Inputs!K16*(1-Inputs!N16) -> 10770.665 | L12: =Inputs!L16+Inputs!M16 -> 47916 | M12: =G12-K12 -> 12152.335 | N12: =C12-L12 -> 21129 | O12: =IF(ABS(N12)<10,"N/M",M12/N12) -> 0.57514956
A13: =Inputs!A17 -> Palantir (PLTR) | B13: =Inputs!$B$4+Inputs!I17*Inputs!$B$5 -> 0.13545 | C13: =Inputs!E17+Inputs!F17 -> 7500 | D13: =IF(C13=0,0,Inputs!E17/C13) -> 1 | E13: =IF(C13=0,0,Inputs!F17/C13) -> 0 | F13: =D13*B13+E13*Inputs!J17*(1-Inputs!H17) -> 0.13545 | G13: =Inputs!C17*(1-Inputs!H17) -> 1392.79 | H13: =IF(C13=0,0,G13/C13) -> 0.18570533 | I13: =IF(Inputs!E17=0,0,Inputs!D17/Inputs!E17) -> 0.21666667 | J13: =IF(Inputs!G17=0,0,Inputs!D17/Inputs!G17) -> 0.18258427 | K13: =Inputs!K17*(1-Inputs!N17) -> 296.8976 | L13: =Inputs!L17+Inputs!M17 -> 5094 | M13: =G13-K13 -> 1095.8924 | N13: =C13-L13 -> 2406 | O13: =IF(ABS(N13)<10,"N/M",M13/N13) -> 0.45548313
A14: =Inputs!A18 -> Tesla (TSLA) | B14: =Inputs!$B$4+Inputs!I18*Inputs!$B$5 -> 0.15635 | C14: =Inputs!E18+Inputs!F18 -> 84700 | D14: =IF(C14=0,0,Inputs!E18/C14) -> 0.97874852 | E14: =IF(C14=0,0,Inputs!F18/C14) -> 0.021251476 | F14: =D14*B14+E14*Inputs!J18*(1-Inputs!H18) -> 0.15341517 | G14: =Inputs!C18*(1-Inputs!H18) -> 3179.15 | H14: =IF(C14=0,0,G14/C14) -> 0.037534238 | I14: =IF(Inputs!E18=0,0,Inputs!D18/Inputs!E18) -> 0.045765983 | J14: =IF(Inputs!G18=0,0,Inputs!D18/Inputs!G18) -> 0.027531457 | K14: =Inputs!K18*(1-Inputs!N18) -> 7077.236 | L14: =Inputs!L18+Inputs!M18 -> 80791 | M14: =G14-K14 -> -3898.086 | N14: =C14-L14 -> 3909 | O14: =IF(ABS(N14)<10,"N/M",M14/N14) -> -0.99720798
A15: =Inputs!A19 -> Constellation Software (CSU) | B15: =Inputs!$B$4+Inputs!I19*Inputs!$B$5 -> 0.0821 | C15: =Inputs!E19+Inputs!F19 -> 8821 | D15: =IF(C15=0,0,Inputs!E19/C15) -> 0.483732 | E15: =IF(C15=0,0,Inputs!F19/C15) -> 0.516268 | F15: =D15*B15+E15*Inputs!J19*(1-Inputs!H19) -> 0.056466261 | G15: =Inputs!C19*(1-Inputs!H19) -> 1182.48 | H15: =IF(C15=0,0,G15/C15) -> 0.13405283 | I15: =IF(Inputs!E19=0,0,Inputs!D19/Inputs!E19) -> 0.11999063 | J15: =IF(Inputs!G19=0,0,Inputs!D19/Inputs!G19) -> 0.031661616 | K15: =Inputs!K19*(1-Inputs!N19) -> 1110.417 | L15: =Inputs!L19+Inputs!M19 -> 7454 | M15: =G15-K15 -> 72.063 | N15: =C15-L15 -> 1367 | O15: =IF(ABS(N15)<10,"N/M",M15/N15) -> 0.052716167
... A17: =Inputs!A21 -> Comfort Systems (FIX) | B17: =Inputs!$B$4+Inputs!I21*Inputs!$B$5 -> 0.1294 | C17: =Inputs!E21+Inputs!F21 -> 2594 | D17: =IF(C17=0,0,Inputs!E21/C17) -> 0.94410177 | E17: =IF(C17=0,0,Inputs!F21/C17) -> 0.055898227 | F17: =D17*B17+E17*Inputs!J21*(1-Inputs!H21) -> 0.12490813 | G17: =Inputs!C21*(1-Inputs!H21) -> 1040.165 | H17: =IF(C17=0,0,G17/C17) -> 0.40098882 | I17: =IF(Inputs!E21=0,0,Inputs!D21/Inputs!E21) -> 0.41772152 | J17: =IF(Inputs!G21=0,0,Inputs!D21/Inputs!G21) -> 0.15882627 | K17: =Inputs!K21*(1-Inputs!N21) -> 587.37972 | L17: =Inputs!L21+Inputs!M21 -> 1773.3 | M17: =G17-K17 -> 452.78528 | N17: =C17-L17 -> 820.7 | O17: =IF(ABS(N17)<10,"N/M",M17/N17) -> 0.5517062

Sheet EVA Dashboard
A1: EVA & COMPOUNDER DASHBOARD
A2: Data as of March 13, 2026 | Most recent fiscal year for each company
A4: Company | B4: ROIC | C4: WACC | D4: ROIC-WACC | E4: ROIIC | F4: ROE | G4: ROA | H4: EVA ($M) | I4: Score | J4: Assessment
A5: =Calculations!A4 -> Veeva (VEEV) | B5: =Calculations!H4 -> 0.17256 | C5: =Calculations!F4 -> 0.1019 | D5: =B5-C5 -> 0.07066 | E5: =Calculations!O4 -> 0.87488353 | F5: =Calculations!I4 -> 0.17246154 | G5: =Calculations!J4 -> 0.13188235 | H5: =Calculations!G4-(Calculations!C4*Calculations!F4) -> 459.29 | I5: =IF(B5>C5,1,0)+IF(B5>0.15,1,0)+IF(AND(ISNUMBER(E5),E5>C5),1,0)+IF(F5>0.15,1,0)+IF(H5>0,1,0) -> 5 | J5: =IF(I5>=4,"COMPOUNDER",IF(I5>=2,"POTENTIAL COMPOUNDER","NOT YET A COMPOUNDER")) -> COMPOUNDER
A6: =Calculations!A5 -> ServiceNow (NOW) | B6: =Calculations!H5 -> 0.097540782 | C6: =Calculations!F5 -> 0.087183211 | D6: =B6-C6 -> 0.010357571 | E6: =Calculations!O5 -> 0.11350156 | F6: =Calculations!I5 -> 0.13483493 | G6: =Calculations!J5 -> 0.067132652 | H6: =Calculations!G5-(Calculations!C5*Calculations!F5) -> 149.71869 | I6: =IF(B6>C6,1,0)+IF(B6>0.15,1,0)+IF(AND(ISNUMBER(E6),E6>C6),1,0)+IF(F6>0.15,1,0)+IF(H6>0,1,0) -> 3 | J6: =IF(I6>=4,"COMPOUNDER",IF(I6>=2,"POTENTIAL COMPOUNDER","NOT YET A COMPOUNDER")) -> POTENTIAL COMPOUNDER
A7: =Calculations!A6 -> Intuit (INTU) | B7: =Calculations!H6 -> 0.15334657 | C7: =Calculations!F6 -> 0.095573811 | D7: =B7-C7 -> 0.05777276 | E7: =Calculations!O6 -> 0.76550868 | F7: =Calculations!I6 -> 0.1962963 | G7: =Calculations!J6 -> 0.1046864 | H7: =Calculations!G6-(Calculations!C6*Calculations!F6) -> 1483.7778 | I7: =IF(B7>C7,1,0)+IF(B7>0.15,1,0)+IF(AND(ISNUMBER(E7),E7>C7),1,0)+IF(F7>0.15,1,0)+IF(H7>0,1,0) -> 5 | J7: =IF(I7>=4,"COMPOUNDER",IF(I7>=2,"POTENTIAL COMPOUNDER","NOT YET A COMPOUNDER")) -> COMPOUNDER
A8: =Calculations!A7 -> Adobe (ADBE) | B8: =Calculations!H7 -> 0.39836797 | C8: =Calculations!F7 -> 0.094594797 | D8: =B8-C8 -> 0.30377317 | E8: =Calculations!O7 -> -0.89358632 | F8: =Calculations!I7 -> 0.61343887 | G8: =Calculations!J7 -> 0.24172769 | H8: =Calculations!G7-(Calculations!C7*Calculations!F7) -> 5417.187 | I8: =IF(B8>C8,1,0)+IF(B8>0.15,1,0)+IF(AND(ISNUMBER(E8),E8>C8),1,0)+IF(F8>0.15,1,0)+IF(H8>0,1,0) -> 4 | J8: =IF(I8>=4,"COMPOUNDER",IF(I8>=2,"POTENTIAL COMPOUNDER","NOT YET A COMPOUNDER")) -> COMPOUNDER
A9: =Calculations!A8 -> Shopify (SHOP) | B9: =Calculations!H8 -> 0.087686699 | C9: =Calculations!F8 -> 0.195386 | D9: =B9-C9 -> -0.1076993 | E9: =Calculations!O8 -> 0.18897722 | F9: =Calculations!I8 -> 0.091367921 | G9: =Calculations!J8 -> 0.081045493 | H9: =Calculations!G8-(Calculations!C8*Calculations!F8) -> -1471.2802 | I9: =IF(B9>C9,1,0)+IF(B9>0.15,1,0)+IF(AND(ISNUMBER(E9),E9>C9),1,0)+IF(F9>0.15,1,0)+IF(H9>0,1,0) -> 0 | J9: =IF(I9>=4,"COMPOUNDER",IF(I9>=2,"POTENTIAL COMPOUNDER","NOT YET A COMPOUNDER")) -> NOT YET A COMPOUNDER
A10: =Calculations!A9 -> Axon (AXON) | B10: =Calculations!H9 -> -0.0097069648 | C10: =Calculations!F9 -> 0.09563478 | D10: =B10-C10 -> -0.10534175 | E10: =Calculations!O9 -> -0.052483792 | F10: =Calculations!I9 -> 0.038452051 | G10: =Calculations!J9 -> 0.017814286 | H10: =Calculations!G9-(Calculations!C9*Calculations!F9) -> -532.39718 | I10: =IF(B10>C10,1,0)+IF(B10>0.15,1,0)+IF(AND(ISNUMBER(E10),E10>C10),1,0)+IF(F10>0.15,1,0)+IF(H10>0,1,0) -> 0 | J10: =IF(I10>=4,"COMPOUNDER",IF(I10>=2,"POTENTIAL COMPOUNDER","NOT YET A COMPOUNDER")) -> NOT YET A COMPOUNDER
A11: =Calculations!A10 -> BillionToOne (BLLN) | B11: =Calculations!H10 -> 0.028839655 | C11: =Calculations!F10 -> 0.11231622 | D11: =B11-C11 -> -0.083476568 | E11: =Calculations!O10 -> 0.2371831 | F11: =Calculations!I10 -> 0.0060404082 | G11: =Calculations!J10 -> 0.0048333333 | H11: =Calculations!G10-(Calculations!C10*Calculations!F10) -> -44.45962 | I11: =IF(B11>C11,1,0)+IF(B11>0.15,1,0)+IF(AND(ISNUMBER(E11),E11>C11),1,0)+IF(F11>0.15,1,0)+IF(H11>0,1,0) -> 1 | J11: =IF(I11>=4,"COMPOUNDER",IF(I11>=2,"POTENTIAL COMPOUNDER","NOT YET A COMPOUNDER")) -> NOT YET A COMPOUNDER
A12: =Calculations!A11 -> Intuitive Surgical (ISRG) | B12: =Calculations!H11 -> 0.12902491 | C12: =Calculations!F11 -> 0.13545 | D12: =B12-C12 -> -0.0064250864 | E12: =Calculations!O11 -> 0.16947274 | F12: =Calculations!I11 -> 0.16163193 | G12: =Calculations!J11 -> 0.14174691 | H12: =Calculations!G11-(Calculations!C11*Calculations!F11) -> -115.2789 | I12: =IF(B12>C12,1,0)+IF(B12>0.15,1,0)+IF(AND(ISNUMBER(E12),E12>C12),1,0)+IF(F12>0.15,1,0)+IF(H12>0,1,0) -> 2 | J12: =IF(I12>=4,"COMPOUNDER",IF(I12>=2,"POTENTIAL COMPOUNDER","NOT YET A COMPOUNDER")) -> POTENTIAL COMPOUNDER
A13: =Calculations!A12 -> Eli Lilly (LLY) | B13: =Calculations!H12 -> 0.33200087 | C13: =Calculations!F12 -> 0.038388744 | D13: =B13-C13 -> 0.29361212 | E13: =Calculations!O12 -> 0.57514956 | F13: =Calculations!I12 -> 0.77633314 | G13: =Calculations!J12 -> 0.18315018 | H13: =Calculations!G12-(Calculations!C12*Calculations!F12) -> 20272.449 | I13: =IF(B13>C13,1,0)+IF(B13>0.15,1,0)+IF(AND(ISNUMBER(E13),E13>C13),1,0)+IF(F13>0.15,1,0)+IF(H13>0,1,0) -> 5 | J13: =IF(I13>=4,"COMPOUNDER",IF(I13>=2,"POTENTIAL COMPOUNDER","NOT YET A COMPOUNDER")) -> COMPOUNDER
A14: =Calculations!A13 -> Palantir (PLTR) | B14: =Calculations!H13 -> 0.18570533 | C14: =Calculations!F13 -> 0.13545 | D14: =B14-C14 -> 0.050255333 | E14: =Calculations!O13 -> 0.45548313 | F14: =Calculations!I13 -> 0.21666667 | G14: =Calculations!J13 -> 0.18258427 | H14: =Calculations!G13-(Calculations!C13*Calculations!F13) -> 376.915 | I14: =IF(B14>C14,1,0)+IF(B14>0.15,1,0)+IF(AND(ISNUMBER(E14),E14>C14),1,0)+IF(F14>0.15,1,0)+IF(H14>0,1,0) -> 5 | J14: =IF(I14>=4,"COMPOUNDER",IF(I14>=2,"POTENTIAL COMPOUNDER","NOT YET A COMPOUNDER")) -> COMPOUNDER
A15: =Calculations!A14 -> Tesla (TSLA) | B15: =Calculations!H14 -> 0.037534238 | C15: =Calculations!F14 -> 0.15341517 | D15: =B15-C15 -> -0.11588093 | E15: =Calculations!O14 -> -0.99720798 | F15: =Calculations!I14 -> 0.045765983 | G15: =Calculations!J14 -> 0.027531457 | H15: =Calculations!G14-(Calculations!C14*Calculations!F14) -> -9815.115 | I15: =IF(B15>C15,1,0)+IF(B15>0.15,1,0)+IF(AND(ISNUMBER(E15),E15>C15),1,0)+IF(F15>0.15,1,0)+IF(H15>0,1,0) -> 0 | J15: =IF(I15>=4,"COMPOUNDER",IF(I15>=2,"POTENTIAL COMPOUNDER","NOT YET A COMPOUNDER")) -> NOT YET A COMPOUNDER
A16: =Calculations!A15 -> Constellation Software (CSU) | B16: =Calculations!H15 -> 0.13405283 | C16: =Calculations!F15 -> 0.056466261 | D16: =B16-C16 -> 0.077586567 | E16: =Calculations!O15 -> 0.052716167 | F16: =Calculations!I15 -> 0.11999063 | G16: =Calculations!J15 -> 0.031661616 | H16: =Calculations!G15-(Calculations!C15*Calculations!F15) -> 684.39111 | I16: =IF(B16>C16,1,0)+IF(B16>0.15,1,0)+IF(AND(ISNUMBER(E16),E16>C16),1,0)+IF(F16>0.15,1,0)+IF(H16>0,1,0) -> 2 | J16: =IF(I16>=4,"COMPOUNDER",IF(I16>=2,"POTENTIAL COMPOUNDER","NOT YET A COMPOUNDER")) -> POTENTIAL COMPOUNDER
... A18: =Calculations!A17 -> Comfort Systems (FIX) | B18: =Calculations!H17 -> 0.40098882 | C18: =Calculations!F17 -> 0.12490813 | D18: =B18-C18 -> 0.27608069 | E18: =Calculations!O17 -> 0.5517062 | F18: =Calculations!I17 -> 0.41772152 | G18: =Calculations!J17 -> 0.15882627 | H18: =Calculations!G17-(Calculations!C17*Calculations!F17) -> 716.15331 | I18: =IF(B18>C18,1,0)+IF(B18>0.15,1,0)+IF(AND(ISNUMBER(E18),E18>C18),1,0)+IF(F18>0.15,1,0)+IF(H18>0,1,0) -> 5 | J18: =IF(I18>=4,"COMPOUNDER",IF(I18>=2,"POTENTIAL COMPOUNDER","NOT YET A COMPOUNDER")) -> COMPOUNDER

Sheet Veeva Projection
A1: VEEVA SYSTEMS (VEEV) - PROJECTED EVA: FY2025 to FY2030
A3: Assumptions:
A4: - Salesforce royalties (~$120M/yr) fully eliminated by FY2027
A5: - AI agent revenue begins FY2028, scales through FY2030
A6: - Management target: $6B revenue by 2030, 35%+ operating margin
A7: - Beta declines as business matures (1.10 -> 1.00)
A8: - Debt remains at $0 (Veeva has no debt)
A10: Year | B10: Revenue ($M) | C10: EBIT Margin | D10: EBIT ($M) | E10: Tax Rate | F10: NOPAT ($M) | G10: Equity ($M) | H10: Beta | I10: WACC | J10: ROIC | K10: ROIC-WACC | L10: EVA ($M) | M10: Verdict
A11: FY2025 (Actual) | B11: 2756 | C11: 0.251 | D11: =B11*C11 -> 691.756 | E11: 0.223 | F11: =D11*(1-E11) -> 537.49441 | G11: 5832 | H11: 1.1 | I11: =Inputs!$B$4+H11*Inputs!$B$5 -> 0.103 | J11: =IF(G11=0,0,F11/G11) -> 0.092162965 | K11: =J11-I11 -> -0.010837035 | L11: =F11-(G11*I11) -> -63.201588 | M11: =IF(L11>0,"CREATING VALUE","DESTROYING VALUE") -> DESTROYING VALUE
A12: FY2026 (Actual) | B12: 3195 | C12: 0.45 | D12: =B12*C12 -> 1437.75 | E12: 0.22 | F12: =D12*(1-E12) -> 1121.445 | G12: 6500 | H12: 1.08 | I12: =Inputs!$B$4+H12*Inputs!$B$5 -> 0.1019 | J12: =IF(G12=0,0,F12/G12) -> 0.17253 | K12: =J12-I12 -> 0.07063 | L12: =F12-(G12*I12) -> 459.095 | M12: =IF(L12>0,"CREATING VALUE","DESTROYING VALUE") -> CREATING VALUE
A13: FY2027 (Guided) | B13: 3590 | C13: 0.44 | D13: =B13*C13 -> 1579.6 | E13: 0.22 | F13: =D13*(1-E13) -> 1232.088 | G13: 7200 | H13: 1.06 | I13: =Inputs!$B$4+H13*Inputs!$B$5 -> 0.1008 | J13: =IF(G13=0,0,F13/G13) -> 0.17112333 | K13: =J13-I13 -> 0.070323333 | L13: =F13-(G13*I13) -> 506.328 | M13: =IF(L13>0,"CREATING VALUE","DESTROYING VALUE") -> CREATING VALUE
A14: FY2028 (Projected) | B14: 4100 | C14: 0.4 | D14: =B14*C14 -> 1640 | E14: 0.22 | F14: =D14*(1-E14) -> 1279.2 | G14: 8000 | H14: 1.04 | I14: =Inputs!$B$4+H14*Inputs!$B$5 -> 0.0997 | J14: =IF(G14=0,0,F14/G14) -> 0.1599 | K14: =J14-I14 -> 0.0602 | L14: =F14-(G14*I14) -> 481.6 | M14: =IF(L14>0,"CREATING VALUE","DESTROYING VALUE") -> CREATING VALUE
A15: FY2029 (Projected) | B15: 5000 | C15: 0.37 | D15: =B15*C15 -> 1850 | E15: 0.22 | F15: =D15*(1-E15) -> 1443 | G15: 9000 | H15: 1.02 | I15: =Inputs!$B$4+H15*Inputs!$B$5 -> 0.0986 | J15: =IF(G15=0,0,F15/G15) -> 0.16033333 | K15: =J15-I15 -> 0.061733333 | L15: =F15-(G15*I15) -> 555.6 | M15: =IF(L15>0,"CREATING VALUE","DESTROYING VALUE") -> CREATING VALUE
A16: FY2030 (Target) | B16: 6000 | C16: 0.35 | D16: =B16*C16 -> 2100 | E16: 0.22 | F16: =D16*(1-E16) -> 1638 | G16: 10000 | H16: 1 | I16: =Inputs!$B$4+H16*Inputs!$B$5 -> 0.0975 | J16: =IF(G16=0,0,F16/G16) -> 0.1638 | K16: =J16-I16 -> 0.0663 | L16: =F16-(G16*I16) -> 663 | M16: =IF(L16>0,"CREATING VALUE","DESTROYING VALUE") -> CREATING VALUE

Sheet Formulas Guide
A1: FORMULAS & DEFINITIONS GUIDE
A3: Metric | B3: Description | C3: Formula
A4: NOPAT | B4: Net Operating Profit After Tax | C4: EBIT x (1 - Tax Rate)
A5: Capital Invested | B5: Total capital used to run business | C5: Equity + Interest-Bearing Debt
A6: WACC | B6: Weighted Average Cost of Capital | C6: (Eq% x Cost of Equity) + (Debt% x Cost of Debt x (1-Tax))
A7: Cost of Equity | B7: Return equity investors demand (CAPM) | C7: Risk-Free Rate + Beta x Market Risk Premium
A8: ROIC | B8: Return on Invested Capital | C8: NOPAT / Capital Invested
A9: EVA | B9: Economic Value Added | C9: NOPAT - (Capital Invested x WACC)
A10: ROE | B10: Return on Equity | C10: Net Income / Shareholders Equity
A11: ROA | B11: Return on Assets | C11: Net Income / Total Assets
A12: ROIIC | B12: Return on Incremental Invested Capital | C12: Change in NOPAT / Change in Capital Invested
A13: ROIC-WACC Spread | B13: Value creation signal | C13: ROIC - WACC (positive = creating value)
A16: COMPOUNDER SCORING (5 points possible):
A17: Points | B17: Criteria | C17: What It Means
A18: 1 point | B18: ROIC > WACC | C18: Company earns above its cost of capital
A19: 1 point | B19: ROIC > 15% | C19: High absolute return on capital
A20: 1 point | B20: ROIIC > WACC | C20: Reinvesting incremental capital at returns above cost
A21: 1 point | B21: ROE > 15% | C21: Strong return to equity holders
A22: 1 point | B22: EVA > 0 | C22: Creating economic value in absolute dollars
A24: Score 4-5: COMPOUNDER
A25: Score 2-3: POTENTIAL COMPOUNDER
A26: Score 0-1: NOT YET A COMPOUNDER
A28: Source: Based on "Forget ROE. This Is the Metric That Actually Matters" - Jimmy's Journal, July 2025
